{
 "as_of": "2026-06-03 (GLD 4.02, SOXX 3.02)",
 "note": "Within-OOS-window decay check (early-half vs late-half Sharpe). All edges HOLDING.",
 "edges": {
  "GLD": {
   "calmar": 4.0204,
   "cell": "ker+trend_scan+regime_gmm + dd_overlay",
   "sharpe_early": 1.8113,
   "sharpe_late": 3.0516,
   "status": "holding (strengthening)"
  },
  "SOXX": {
   "calmar": 3.0248,
   "cell": "ker+trend_scan+bgm t0.50",
   "sharpe_early": 0.4913,
   "sharpe_late": 2.1186,
   "status": "holding (strengthening)"
  },
  "UUP": {
   "calmar": 1.2958,
   "cell": "bgm+ker imbalance",
   "sharpe_early": 1.2815,
   "sharpe_late": 1.0221,
   "status": "holding"
  }
 }
}